odoo/addons/membership_withdrawal/README.rst
odoo/addons/membership_withdrawal/__init__.py
odoo/addons/membership_withdrawal/__manifest__.py
odoo/addons/membership_withdrawal/data/membership_withdrawal_reason_data.xml
odoo/addons/membership_withdrawal/i18n/am.po
odoo/addons/membership_withdrawal/i18n/ar.po
odoo/addons/membership_withdrawal/i18n/bg.po
odoo/addons/membership_withdrawal/i18n/bs.po
odoo/addons/membership_withdrawal/i18n/ca.po
odoo/addons/membership_withdrawal/i18n/cs.po
odoo/addons/membership_withdrawal/i18n/da.po
odoo/addons/membership_withdrawal/i18n/de.po
odoo/addons/membership_withdrawal/i18n/el_GR.po
odoo/addons/membership_withdrawal/i18n/en_GB.po
odoo/addons/membership_withdrawal/i18n/es.po
odoo/addons/membership_withdrawal/i18n/es_AR.po
odoo/addons/membership_withdrawal/i18n/es_CL.po
odoo/addons/membership_withdrawal/i18n/es_CO.po
odoo/addons/membership_withdrawal/i18n/es_CR.po
odoo/addons/membership_withdrawal/i18n/es_DO.po
odoo/addons/membership_withdrawal/i18n/es_EC.po
odoo/addons/membership_withdrawal/i18n/es_ES.po
odoo/addons/membership_withdrawal/i18n/es_MX.po
odoo/addons/membership_withdrawal/i18n/es_PE.po
odoo/addons/membership_withdrawal/i18n/es_PY.po
odoo/addons/membership_withdrawal/i18n/es_VE.po
odoo/addons/membership_withdrawal/i18n/et.po
odoo/addons/membership_withdrawal/i18n/fa.po
odoo/addons/membership_withdrawal/i18n/fi.po
odoo/addons/membership_withdrawal/i18n/fr.po
odoo/addons/membership_withdrawal/i18n/fr_CA.po
odoo/addons/membership_withdrawal/i18n/fr_CH.po
odoo/addons/membership_withdrawal/i18n/gl.po
odoo/addons/membership_withdrawal/i18n/gl_ES.po
odoo/addons/membership_withdrawal/i18n/he.po
odoo/addons/membership_withdrawal/i18n/hr.po
odoo/addons/membership_withdrawal/i18n/hr_HR.po
odoo/addons/membership_withdrawal/i18n/hu.po
odoo/addons/membership_withdrawal/i18n/id.po
odoo/addons/membership_withdrawal/i18n/it.po
odoo/addons/membership_withdrawal/i18n/ja.po
odoo/addons/membership_withdrawal/i18n/ko.po
odoo12_addon_membership_withdrawal-12.0.1.1.0.dist-info/METADATA
odoo12_addon_membership_withdrawal-12.0.1.1.0.dist-info/WHEEL
odoo12_addon_membership_withdrawal-12.0.1.1.0.dist-info/top_level.txt
odoo12_addon_membership_withdrawal-12.0.1.1.0.dist-info/RECORD
